{
  "id": "A.CVN.005",
  "title": "Validate version - unsupported version with <x-v-min>",
  "given": [
    "the <x-v>  is included in a  request header",
    "AND  <x-v-min>  is included"
  ],
  "when": [
    "no version between <x-v> and <x-min-v> is supported"
  ],
  "then": {
    "and": [
      "the response has a status of 406",
      " the response body has ErrorListReponse object",
      " error code is \"Header/UnsupportedVersion\""
    ]
  },
  "references": [
    {
      "uri": "https://consumerdatastandardsaustralia.github.io/standards/#http-headers"
    }
  ],
  "negative": false
}